sqlite_history/__init__.py
sqlite_history/__main__.py
sqlite_history/cli.py
sqlite_history/sql.py
sqlite_history-0.1.dist-info/LICENSE
sqlite_history-0.1.dist-info/METADATA
sqlite_history-0.1.dist-info/WHEEL
sqlite_history-0.1.dist-info/top_level.txt
sqlite_history-0.1.dist-info/RECORD
