Metadata-Version: 2.1
Name: sqlite-history
Version: 0.1
Summary: Track changes to SQLite tables using triggers
Home-page: https://github.com/simonw/sqlite-history
Author: Simon Willison
License: Apache License, Version 2.0
Project-URL: Issues, https://github.com/simonw/sqlite-history/issues
Project-URL: CI, https://github.com/simonw/sqlite-history/actions
Project-URL: Changelog, https://github.com/simonw/sqlite-history/releases
Requires-Python: >=3.7
License-File: LICENSE
Provides-Extra: test
Requires-Dist: pytest ; extra == 'test'
Requires-Dist: sqlite-utils ; extra == 'test'
Requires-Dist: cogapp ; extra == 'test'
